MANIFEST.in
README.txt
setup.cfg
setup.py
atreal/__init__.py
atreal/__init__.pyc
atreal.monkeyplone.egg-info/PKG-INFO
atreal.monkeyplone.egg-info/SOURCES.txt
atreal.monkeyplone.egg-info/dependency_links.txt
atreal.monkeyplone.egg-info/entry_points.txt
atreal.monkeyplone.egg-info/namespace_packages.txt
atreal.monkeyplone.egg-info/not-zip-safe
atreal.monkeyplone.egg-info/requires.txt
atreal.monkeyplone.egg-info/top_level.txt
atreal/monkeyplone/__init__.py
atreal/monkeyplone/__init__.pyc
atreal/monkeyplone/configure.zcml
atreal/monkeyplone/patch.py
atreal/monkeyplone/patch.pyc
atreal/monkeyplone/profiles/default/actions.xml
atreal/monkeyplone/profiles/default/metadata.xml
docs/HISTORY.txt
docs/INSTALL.txt
docs/LICENSE.GPL
docs/LICENSE.txt