Metadata-Version: 1.0
Name: atreal.monkeyplone
Version: 2.0.0
Summary: A Patch for Plone cut/copy/paste/delete permissions
Home-page: http://www.atreal.net/
Author: atReal
Author-email: contact@atreal.net
License: GPL
Platform: UNKNOWN
Classifier: Framework :: Plone
Classifier: Framework :: Zope2
Classifier: Framework :: Zope3
Classifier: Programming Language :: Python
Classifier: Topic :: Software Development :: Libraries :: Python Modules
